README.md
setup.py
typhoon/__init__.py
typhoon/async_rest.py
typhoon/log.py
typhoon/rest.py
typhoon/settings.py
typhoon/status.py
typhoon/util.py
typhoon/web.py
typhoon/coroutine/__init__.py
typhoon/coroutine/gen_new.py
typhoon/coroutine/gen_old.py
typhoon/coroutine/native.py
typhoon_web.egg-info/PKG-INFO
typhoon_web.egg-info/SOURCES.txt
typhoon_web.egg-info/dependency_links.txt
typhoon_web.egg-info/requires.txt
typhoon_web.egg-info/top_level.txt