Metadata-Version: 2.1
Name: typhoon-web
Version: 2.0.0
Summary: A wrapper around the Tornado web framework that supports logs with traceId.
Home-page: https://github.com/WeiJiHsiao/typhoon
Author: WeiJi Hsiao
Author-email: weiji.hsiao@gmail.com
License: MIT License
Platform: UNKNOWN
Classifier: Intended Audience :: Developers
Classifier: Operating System :: OS Independent
Classifier: Topic :: Software Development :: Libraries :: Python Modules
